data_whiz/__init__.py
data_whiz/curved_surface.py
data_whiz-0.0.2.dist-info/LICENCE
data_whiz-0.0.2.dist-info/METADATA
data_whiz-0.0.2.dist-info/WHEEL
data_whiz-0.0.2.dist-info/top_level.txt
data_whiz-0.0.2.dist-info/RECORD
