Metadata-Version: 2.1
Name: data-whiz
Version: 0.0.2
Summary: this package can be used to calculate distance between two points in the curved surface
Home-page: https://github.com/hareeharan03/python-libraries
Author: Hareeharan Elangovan
Author-email: Hareeharan1999@gmail.com
Project-URL: Bug Tracker, https://github.com/hareeharan03/python-libraries/issues
Classifier: Programming Language :: Python :: 3
Classifier: License :: OSI Approved :: MIT License
Classifier: Operating System :: OS Independent
Requires-Python: >=3.6
License-File: LICENCE
